{
  "player": {
    "sprites": {
      "horizontal": {
        "texture": "art/playerGrey_walk1.png",
        "width": 65,
        "height": 65,
        "frameCount": 2,
        "frameTime": 0.1,
        "animated": true
      },
      "vertical": {
        "texture": "art/playerGrey_up1.png",
        "width": 65,
        "height": 65,
        "frameCount": 2,
        "frameTime": 0.1,
        "animated": true
      }
    },
    "collider": {
      "width": 55,
      "height": 55,
      "isTrigger": false
    },
    "speed": 400.0,
    "startPosition": { "x": 640, "y": 600 },
    "combat": {
      "weapon": {
        "damage": 20.0,
        "fireRate": 5.0,
        "ammoCount": 100,
        "maxAmmo": 100,
        "range": 800.0
      },
      "aimingLine": {
        "maxRange": 800.0,
        "dotCount": 20,
        "dotSpacing": 40.0
      }
    }
  },
  "mobs": {
    "flying": {
      "sprite": {
        "texture": "art/enemyFlyingAlt_1.png",
        "width": 60,
        "height": 60,
        "frameCount": 2,
        "frameTime": 0.1,
        "animated": true
      },
      "collider": {
        "width": 50,
        "height": 50,
        "isTrigger": false
      },
      "speedRange": { "min": 120.0, "max": 180.0 }
    },
    "swimming": {
      "sprite": {
        "texture": "art/enemySwimming_1.png",
        "width": 60,
        "height": 60,
        "frameCount": 2,
        "frameTime": 0.1,
        "animated": true
      },
      "collider": {
        "width": 50,
        "height": 50,
        "isTrigger": false
      },
      "speedRange": { "min": 120.0, "max": 180.0 }
    },
    "walking": {
      "sprite": {
        "texture": "art/enemyWalking_1.png",
        "width": 60,
        "height": 60,
        "frameCount": 2,
        "frameTime": 0.1,
        "animated": true
      },
      "collider": {
        "width": 50,
        "height": 50,
        "isTrigger": false
      },
      "speedRange": { "min": 120.0, "max": 180.0 }
    },
    "mobKing": {
      "sprites": {
        "horizontal": {
          "texture": "art/enemyFlyingAlt_1.png",
          "width": 160,
          "height": 160,
          "frameCount": 2,
          "frameTime": 0.2,
          "animated": true
        },
        "vertical": {
          "texture": "art/enemyFlyingUp_1.png",
          "width": 160,
          "height": 160,
          "frameCount": 2,
          "frameTime": 0.2,
          "animated": true
        }
      },
      "collider": {
        "width": 130,
        "height": 130,
        "isTrigger": false
      },
      "speedRange": { "min": 80.0, "max": 100.0 },
      "combat": {
        "health": 1000.0,
        "damage": 30.0,
        "fireRate": 2.0,
        "range": 600.0,
        "projectileSpeed": 400.0
      },
      "startPosition": { "x": 1000, "y": 300 }
    }
  },
  "defaultMobCombat": {
    "damage": 15.0,
    "fireRate": 2.0,
    "range": 400.0,
    "projectileSpeed": 300.0
  },
  "ui": {
    "mobKingHealth": {
      "position": { "x": 280, "y": 10 },
      "text": {
        "format": "Mob King: {current}/{max}",
        "font": "fonts/Xolonium-Regular.ttf",
        "fontSize": 20
      },
      "colors": {
        "healthy": { "r": 255, "g": 255, "b": 255, "a": 255 },
        "warning": { "r": 255, "g": 255, "b": 0, "a": 255 },
        "critical": { "r": 255, "g": 0, "b": 0, "a": 255 }
      },
      "thresholds": {
        "warning": 0.6,
        "critical": 0.3
      }
    },
    "scoreDisplay": {
      "position": { "x": 10, "y": 10 },
      "text": "Score: 0",
      "font": "fonts/Xolonium-Regular.ttf",
      "fontSize": 24,
      "color": { "r": 255, "g": 255, "b": 255, "a": 255 }
    },
    "fpsDisplay": {
      "position": { "x": 10, "y": 50 },
      "text": "FPS: 60",
      "font": "fonts/Xolonium-Regular.ttf",
      "fontSize": 18,
      "color": { "r": 255, "g": 255, "b": 255, "a": 255 }
    },
    "ammoDisplay": {
      "position": { "x": 10, "y": 80 },
      "text": "Ammo: 30/30",
      "font": "fonts/Xolonium-Regular.ttf",
      "fontSize": 20,
      "color": { "r": 255, "g": 255, "b": 0, "a": 255 }
    },
    "levelDisplay": {
      "position": { "x": 10, "y": 110 },
      "text": "Level: 1 - Time: 45s",
      "font": "fonts/Xolonium-Regular.ttf",
      "fontSize": 20,
      "color": { "r": 0, "g": 255, "b": 255, "a": 255 }
    },
    "gameMessage": {
      "position": { "x": 640, "y": 360 },
      "text": "Bloodstrike 2D!",
      "font": "fonts/Xolonium-Regular.ttf",
      "fontSize": 32,
      "color": { "r": 255, "g": 255, "b": 255, "a": 255 }
    }
  },
  "audio": {
    "backgroundMusic": {
      "name": "background",
      "file": "art/House In a Forest Loop.ogg"
    },
    "soundEffects": {
      "gameOver": {
        "name": "gameover",
        "file": "art/gameover.wav"
      },
      "gunShot": {
        "name": "gunshot",
        "file": "art/ak47.mp3"
      }
    },
    "settings": {
      "musicVolume": 64,
      "sfxVolume": 80
    }
  },
  "gameSettings": {
    "mobSpawnInterval": 0.5,
    "scorePerSecond": 10,
    "screenSize": { "width": 1280, "height": 720 }
  },
  "menus": {
    "mainMenu": {
      "title": "BLOODSTRIKE 2D",
      "titlePosition": { "x": 640, "y": 150 },
      "titleFont": "fonts/Xolonium-Regular.ttf",
      "titleSize": 48,
      "options": [
        {
          "text": "Single Player",
          "action": "singleplayer"
        },
        {
          "text": "Dual Player",
          "action": "dualplayer"
        },
        {
          "text": "Multiplayer",
          "action": "multiplayer"
        },
        {
          "text": "Settings",
          "action": "settings"
        },
        {
          "text": "Quit",
          "action": "quit"
        }
      ],
      "optionFont": "fonts/Xolonium-Regular.ttf",
      "optionSize": 32,
      "optionSpacing": 60,
      "startPosition": { "x": 640, "y": 250 },
      "colors": {
        "normal": { "r": 255, "g": 255, "b": 255, "a": 255 },
        "selected": { "r": 255, "g": 255, "b": 0, "a": 255 },
        "background": { "r": 32, "g": 32, "b": 64, "a": 255 }
      }
    },
    "multiplayerMenu": {
      "title": "MULTIPLAYER",
      "titlePosition": { "x": 640, "y": 150 },
      "titleFont": "fonts/Xolonium-Regular.ttf",
      "titleSize": 48,
      "options": [
        {
          "text": "Host Game",
          "action": "host"
        },
        {
          "text": "Join Game",
          "action": "join"
        },
        {
          "text": "Back",
          "action": "back"
        }
      ],
      "optionFont": "fonts/Xolonium-Regular.ttf",
      "optionSize": 32,
      "optionSpacing": 60,
      "startPosition": { "x": 640, "y": 250 },
      "colors": {
        "normal": { "r": 255, "g": 255, "b": 255, "a": 255 },
        "selected": { "r": 255, "g": 255, "b": 0, "a": 255 },
        "background": { "r": 32, "g": 32, "b": 64, "a": 255 }
      }
    },
    "lobbyWaiting": {
      "title": "WAITING FOR PLAYERS...",
      "titlePosition": { "x": 640, "y": 200 },
      "titleFont": "fonts/Xolonium-Regular.ttf",
      "titleSize": 36,
      "options": [
        {
          "text": "Cancel",
          "action": "back"
        }
      ],
      "optionFont": "fonts/Xolonium-Regular.ttf",
      "optionSize": 28,
      "optionSpacing": 60,
      "startPosition": { "x": 640, "y": 400 },
      "colors": {
        "normal": { "r": 255, "g": 255, "b": 255, "a": 255 },
        "selected": { "r": 255, "g": 255, "b": 0, "a": 255 },
        "background": { "r": 32, "g": 32, "b": 64, "a": 255 }
      },
      "statusText": {
        "position": { "x": 640, "y": 300 },
        "text": "Connection Status: Waiting...",
        "font": "fonts/Xolonium-Regular.ttf",
        "fontSize": 24,
        "color": { "r": 200, "g": 200, "b": 200, "a": 255 }
      }
    }
  }
}
